dotpack/__init__.py
dotpack/ledbag.py
dotpack/microblocks_client.py
dotpack/simulator_tk.py
dotpack/utils.py
dotpack/src/seguiemj.ttf
dotpack_tk-0.0.5.dist-info/AUTHORS.rst
dotpack_tk-0.0.5.dist-info/LICENSE
dotpack_tk-0.0.5.dist-info/METADATA
dotpack_tk-0.0.5.dist-info/WHEEL
dotpack_tk-0.0.5.dist-info/entry_points.txt
dotpack_tk-0.0.5.dist-info/top_level.txt
dotpack_tk-0.0.5.dist-info/RECORD
