Metadata-Version: 2.1
Name: dotpack-tk
Version: 0.0.5
Summary: A simulator(tkinter-based) for dotPack.
Home-page: https://github.com/longan-link/dotpack_pyclient
Author: Wenjie Wu
Author-email: wuwenjie718@gmail.com
License: GNU General Public License v3
Keywords: dotpack
Platform: UNKNOWN
Classifier: Development Status :: 2 - Pre-Alpha
Classifier: Intended Audience :: Developers
Classifier: License :: OSI Approved :: GNU General Public License v3 (GPLv3)
Classifier: Natural Language :: English
Classifier: Programming Language :: Python :: 3.6
Classifier: Programming Language :: Python :: 3.7
Classifier: Programming Language :: Python :: 3.8
Requires-Dist: Pillow (==9.0.1)
